fds/__init__.py
fds/sdk/__init__.py
fds/sdk/FactSetMergersandAcquisitions/__init__.py
fds/sdk/FactSetMergersandAcquisitions/api_client.py
fds/sdk/FactSetMergersandAcquisitions/configuration.py
fds/sdk/FactSetMergersandAcquisitions/exceptions.py
fds/sdk/FactSetMergersandAcquisitions/model_utils.py
fds/sdk/FactSetMergersandAcquisitions/rest.py
fds/sdk/FactSetMergersandAcquisitions/api/__init__.py
fds/sdk/FactSetMergersandAcquisitions/api/deals_api.py
fds/sdk/FactSetMergersandAcquisitions/apis/__init__.py
fds/sdk/FactSetMergersandAcquisitions/model/__init__.py
fds/sdk/FactSetMergersandAcquisitions/model/advisor_participant.py
fds/sdk/FactSetMergersandAcquisitions/model/advisors.py
fds/sdk/FactSetMergersandAcquisitions/model/buyers_advisor.py
fds/sdk/FactSetMergersandAcquisitions/model/deal_company.py
fds/sdk/FactSetMergersandAcquisitions/model/deal_ids.py
fds/sdk/FactSetMergersandAcquisitions/model/deal_public.py
fds/sdk/FactSetMergersandAcquisitions/model/deal_value.py
fds/sdk/FactSetMergersandAcquisitions/model/deals_public_request.py
fds/sdk/FactSetMergersandAcquisitions/model/deals_public_request_body.py
fds/sdk/FactSetMergersandAcquisitions/model/deals_public_response.py
fds/sdk/FactSetMergersandAcquisitions/model/deals_request.py
fds/sdk/FactSetMergersandAcquisitions/model/deals_request_body.py
fds/sdk/FactSetMergersandAcquisitions/model/deals_response.py
fds/sdk/FactSetMergersandAcquisitions/model/detail.py
fds/sdk/FactSetMergersandAcquisitions/model/details_request.py
fds/sdk/FactSetMergersandAcquisitions/model/details_request_body.py
fds/sdk/FactSetMergersandAcquisitions/model/details_response.py
fds/sdk/FactSetMergersandAcquisitions/model/error_object.py
fds/sdk/FactSetMergersandAcquisitions/model/error_response.py
fds/sdk/FactSetMergersandAcquisitions/model/ids.py
fds/sdk/FactSetMergersandAcquisitions/model/participant.py
fds/sdk/FactSetMergersandAcquisitions/model/sellers_advisor.py
fds/sdk/FactSetMergersandAcquisitions/model/status.py
fds_sdk_factsetmergersandacquisitions-1.1.2.dist-info/licenses/LICENSE
fds_sdk_factsetmergersandacquisitions-1.1.2.dist-info/METADATA
fds_sdk_factsetmergersandacquisitions-1.1.2.dist-info/WHEEL
fds_sdk_factsetmergersandacquisitions-1.1.2.dist-info/top_level.txt
fds_sdk_factsetmergersandacquisitions-1.1.2.dist-info/RECORD
